woy/__init__.py
woy/py.typed
woy/woy.py
woy-1.4.dist-info/METADATA
woy-1.4.dist-info/WHEEL
woy-1.4.dist-info/entry_points.txt
woy-1.4.dist-info/licenses/LICENSE
woy-1.4.dist-info/RECORD
